{
  "name": "nimbus/path-publisher",
  "type": "COMPONENT_TYPE_COMPONENT",
  "className": "Ros1Component",
  "instanceName": "",
  "description": "path-publisher\n License: BSD",
  "version": {
    "major": 1,
    "minor": 0,
    "patch": 0,
    "build": ""
  },
  "start": "START_MODE_AUTO",
  "environment": {
    "name": "",
    "ipAddress": "",
    "state": "ENVIRONMENT_STATE_UNLOADED",
    "message": "",
    "progress": 0,
    "requiredDevices": [],
    "ports": [],
    "hostIpAddress": "",
    "variables": [],
    "dockerInfo": {
      "image": "cognimbus/path-publisher:latest",
      "containerId": "",
      "imageSize": 0,
      "commands": [
        "roslaunch",
        "path_publisher",
        "path_publisher.launch",
        "waypoints_file_name:=${waypoints_file_name}",
        "--screen"
      ],
      "privileged": true,
      "gpu": false,
      "networkHost": false,
      "binds": [
        {
          "source": "/opt/nimbus/data/waypoints/",
          "target": "/path_publisher_ws/src/path_publisher/waypoints/"
        }
      ]
    },
    "log": "",
    "convertedCommands": "",
    "onExit": "IGNORE"
  },
  "parameters": {
    "parameters": [
      {
        "name": "waypoints_file_name",
        "description": "",
        "Category": "Static",
        "node": "",
        "stringValue": "square.yaml"
      }
    ]
  },
  "state": "COMPONENT_STATE_UNLOADED",
  "message": "",
  "streams": {
    "inputStreams": [
      {
        "name": "send_path",
        "type": "",
        "description": "",
        "streamMode": "STREAM_MODE_TOPIC",
        "rosTopic": {
          "topic": "/send_path",
          "type": "Messages.std_msgs.Bool",
          "qosProfile": ""
        },
        "latched": false,
        "maxRate": 0,
        "expectedRate": 0
      }
    ],
    "outputStreams": [
      {
        "name": "polygon_path",
        "type": "",
        "description": "",
        "streamMode": "STREAM_MODE_TOPIC",
        "rosTopic": {
          "topic": "/polygon_path",
          "type": "Messages.nav_msgs.Path",
          "qosProfile": ""
        },
        "latched": false,
        "maxRate": 0,
        "expectedRate": 0
      }
    ]
  },
  "requiredDevices": [],
  "tags": {},
  "category": "Algorithms/Navigation",
  "simulation": false,
  "pluginFile": "",
  "license": "BSD",
  "id": ""
}
